anilius/__init__.py
anilius/cache/__init__.py
anilius/cache/cache.py
anilius/cache/exceptions.py
anilius/cache/compressors/__init__.py
anilius/cache/compressors/base.py
anilius/cache/compressors/lz4.py
anilius/cache/serializers/__init__.py
anilius/cache/serializers/base.py
anilius/cache/serializers/json.py
anilius/cache/serializers/msgpack.py
anilius/cli/__init__.py
anilius/cli/anilius.py
anilius/cli/create.py
anilius/cli/main.py
anilius/cli/serve.py
anilius/cli/version.py
anilius/core/__init__.py
anilius/core/app.py
anilius/core/controller.py
anilius/core/model.py
anilius/core/module.py
anilius/core/permission.py
anilius/core/serializer.py
anilius/core/serializer_field.py
anilius/core/service.py
anilius/core/settings.py
anilius/db/__init__.py
anilius/db/db.py
anilius/db/db_session.py
anilius/fields/__init__.py
anilius/fields/boolean.py
anilius/fields/int.py
anilius/fields/string.py
anilius/model/__init__.py
anilius/model/uuid.py
anilius/permissions/__init__.py
anilius/permissions/is_authorize.py
anilius/server/__init__.py
anilius/server/grpcio.py
anilius/server/server.py
anilius/utils/__init__.py
anilius/utils/jwt.py
anilius/utils/random.py
anilius/utils/singleton.py
anilius/utils/uuid.py
anilius/wrappers/__init__.py
anilius/wrappers/service.py
Anilius-2.0.0rc1.dist-info/LICENSE
Anilius-2.0.0rc1.dist-info/METADATA
Anilius-2.0.0rc1.dist-info/WHEEL
Anilius-2.0.0rc1.dist-info/entry_points.txt
Anilius-2.0.0rc1.dist-info/top_level.txt
Anilius-2.0.0rc1.dist-info/RECORD
