Metadata-Version: 2.1
Name: Anilius
Version: 2.0.0rc1
Summary: A high performance grpc micro framework based on python
Home-page: https://github.com/Malivix/Anilius
Author: Mahdi Zarrintareh
Author-email: mza2rintareh@gmail.com
License: UNKNOWN
Platform: UNKNOWN
Classifier: Programming Language :: Python :: 3
Classifier: License :: OSI Approved :: MIT License
Classifier: Operating System :: OS Independent
Requires-Python: >=3.0
License-File: LICENSE
